linux_profiler/__init__.py
linux_profiler/server.py
linux_profiler/collectors/__init__.py
linux_profiler/collectors/base.py
linux_profiler/collectors/cpu.py
linux_profiler/collectors/disk.py
linux_profiler/collectors/memory.py
linux_profiler/collectors/network.py
linux_profiler/collectors/perf.py
linux_profiler/collectors/process.py
linux_profiler/collectors/utils.py
linux_profiler_mcp-1.1.0.dist-info/METADATA
linux_profiler_mcp-1.1.0.dist-info/WHEEL
linux_profiler_mcp-1.1.0.dist-info/entry_points.txt
linux_profiler_mcp-1.1.0.dist-info/licenses/LICENSE
linux_profiler_mcp-1.1.0.dist-info/RECORD
