Metadata-Version: 2.4
Name: linux-profiler-mcp
Version: 1.1.0
Summary: Linux Performance Profiler with MCP Protocol Support and Process Profiling
Project-URL: Homepage, https://github.com/yuezhongtao/linux-profiler-tool
Project-URL: Repository, https://github.com/yuezhongtao/linux-profiler-tool
Project-URL: Issues, https://github.com/yuezhongtao/linux-profiler-tool/issues
Project-URL: Changelog, https://github.com/yuezhongtao/linux-profiler-tool/blob/main/CHANGELOG.md
Author: Linux Profiler Contributors
License: Apache-2.0
License-File: LICENSE
Keywords: flame-graph,linux,mcp,monitoring,perf,performance,profiler,system-metrics
Classifier: Development Status :: 4 - Beta
Classifier: Intended Audience :: Developers
Classifier: Intended Audience :: System Administrators
Classifier: License :: OSI Approved :: Apache Software License
Classifier: Operating System :: POSIX :: Linux
Classifier: Programming Language :: Python :: 3
Classifier: Programming Language :: Python :: 3.10
Classifier: Programming Language :: Python :: 3.11
Classifier: Programming Language :: Python :: 3.12
Classifier: Topic :: Software Development :: Debuggers
Classifier: Topic :: System :: Monitoring
Classifier: Topic :: System :: Systems Administration
Requires-Python: >=3.10
Requires-Dist: mcp>=1.0.0
Requires-Dist: psutil>=5.9.0
Requires-Dist: pydantic>=2.0.0
Requires-Dist: starlette>=0.27.0
Requires-Dist: uvicorn>=0.24.0
Provides-Extra: dev
Requires-Dist: black>=23.0.0; extra == 'dev'
Requires-Dist: pytest-asyncio>=0.21.0; extra == 'dev'
Requires-Dist: pytest>=7.0.0; extra == 'dev'
Requires-Dist: ruff>=0.1.0; extra == 'dev'
